prismdata/__about__.py
prismdata/__init__.py
prismdata/core.py
prismdata-0.0.1.dist-info/METADATA
prismdata-0.0.1.dist-info/WHEEL
prismdata-0.0.1.dist-info/licenses/LICENSE.txt
prismdata-0.0.1.dist-info/RECORD
