Metadata-Version: 2.3
Name: prismdata
Version: 0.0.1
Summary: A Python Package to donwload PRISM data programmatically
Project-URL: Homepage, https://github.com/iamsaswata/prismdata
Project-URL: Documentation, https://prismdata.readthedocs.io
Project-URL: Issues, https://github.com/iamsaswata/prismdata/issues
Project-URL: Source, https://github.com/iamsaswata/prismdata
Author-email: Saswata Nandi <iamsaswata@yahoo.com>
Maintainer-email: Saswata Nandi <iamsaswata@yahoo.com>
License-Expression: MIT
License-File: LICENSE.txt
Classifier: Development Status :: 4 - Beta
Classifier: Programming Language :: Python
Classifier: Programming Language :: Python :: 3.8
Classifier: Programming Language :: Python :: 3.9
Classifier: Programming Language :: Python :: 3.10
Classifier: Programming Language :: Python :: 3.11
Classifier: Programming Language :: Python :: 3.12
Classifier: Topic :: Scientific/Engineering :: Atmospheric Science
Classifier: Topic :: Scientific/Engineering :: Hydrology
Requires-Python: >=3.8
Requires-Dist: pyproj>=3.3
Requires-Dist: python-dateutil>=2.9.0
Requires-Dist: rasterio>=1.3
Requires-Dist: requests>=2.31.0
Requires-Dist: rioxarray>=0.15.5
Requires-Dist: scipy>=1.13.0
Requires-Dist: xarray>=2022.3.0
